crayons.py
crayons-0.3.1.dist-info/LICENSE
crayons-0.3.1.dist-info/METADATA
crayons-0.3.1.dist-info/WHEEL
crayons-0.3.1.dist-info/top_level.txt
crayons-0.3.1.dist-info/RECORD
