Metadata-Version: 1.2
Name: crayons
Version: 0.3.1
Summary: TextUI colors for Python.
Home-page: https://github.com/MasterOdin/crayons
Author: Kenneth Reitz
Author-email: me@kennethreitz.com
Maintainer: Matthew Peveler
Maintainer-email: matt.peveler@gmail.com
License: MIT
Platform: UNKNOWN
Classifier: License :: OSI Approved :: MIT License
Classifier: Programming Language :: Python
Classifier: Programming Language :: Python :: 2.7
Classifier: Programming Language :: Python :: 3
Classifier: Programming Language :: Python :: 3.4
Classifier: Programming Language :: Python :: 3.5
Classifier: Programming Language :: Python :: 3.6
Classifier: Programming Language :: Python :: 3.7
Classifier: Programming Language :: Python :: Implementation :: CPython
Classifier: Programming Language :: Python :: Implementation :: PyPy
